MITgcm_recipes/__init__.py
MITgcm_recipes/akima1d.so
MITgcm_recipes/data_organization.py
MITgcm_recipes/mod_drown_sosie.so
MITgcm_recipes/monitoring.py
MITgcm_recipes/open_boundary.py
MITgcm_recipes/plotting.py
MITgcm_recipes/regridding.py
MITgcm_recipes/spatial.py
MITgcm_recipes/akima1d.so.dSYM/Contents/Info.plist
MITgcm_recipes/akima1d.so.dSYM/Contents/Resources/DWARF/akima1d.so
MITgcm_recipes/mod_drown_sosie.so.dSYM/Contents/Info.plist
MITgcm_recipes/mod_drown_sosie.so.dSYM/Contents/Resources/DWARF/mod_drown_sosie.so
MITgcm_recipes-0.1.dist-info/METADATA
MITgcm_recipes-0.1.dist-info/WHEEL
MITgcm_recipes-0.1.dist-info/top_level.txt
MITgcm_recipes-0.1.dist-info/RECORD
