Metadata-Version: 2.1
Name: MITgcm-recipes
Version: 0.1
Summary: MITgcm tools for Real World Applications
Home-page: UNKNOWN
Author: Raphael Dussin
Author-email: rdussin@ldeo.columbia.edu
License: GPLv3
Keywords: ocean modeling,BGC
Platform: UNKNOWN
